pybispectra/__init__.py
pybispectra/cfc/__init__.py
pybispectra/cfc/aac.py
pybispectra/cfc/pac.py
pybispectra/cfc/ppc.py
pybispectra/general/__init__.py
pybispectra/general/general.py
pybispectra/tde/__init__.py
pybispectra/tde/tde.py
pybispectra/utils/__init__.py
pybispectra/utils/_defaults.py
pybispectra/utils/_docs.py
pybispectra/utils/_plot.py
pybispectra/utils/_process.py
pybispectra/utils/_utils.py
pybispectra/utils/ged.py
pybispectra/utils/results.py
pybispectra/utils/utils.py
pybispectra/waveshape/__init__.py
pybispectra/waveshape/waveshape.py
pybispectra-1.3.0.dist-info/METADATA
pybispectra-1.3.0.dist-info/WHEEL
pybispectra-1.3.0.dist-info/licenses/LICENSE.txt
pybispectra-1.3.0.dist-info/RECORD
