Metadata-Version: 2.4
Name: pybispectra
Version: 1.3.0
Summary: A Python signal processing package for computing spectral-domain and time-domain interactions using the bispectrum.
Project-URL: Bug Tracker, https://github.com/braindatalab/PyBispectra/issues
Project-URL: Homepage, https://github.com/braindatalab/PyBispectra
Author-email: "Thomas S. Binns" <t.s.binns@outlook.com>
License-File: LICENSE.txt
Classifier: License :: OSI Approved :: MIT License
Classifier: Operating System :: OS Independent
Classifier: Programming Language :: Python :: 3
Requires-Python: >=3.10
Requires-Dist: joblib>=1.2
Requires-Dist: matplotlib>=3.6
Requires-Dist: mne>=1.7
Requires-Dist: numba>=0.56
Requires-Dist: numpy>=1.22
Requires-Dist: scikit-learn>=1.1
Requires-Dist: scipy>=1.8
Provides-Extra: dev
Requires-Dist: codespell; extra == 'dev'
Requires-Dist: coverage; extra == 'dev'
Requires-Dist: ipykernel; extra == 'dev'
Requires-Dist: ipython; extra == 'dev'
Requires-Dist: ipywidgets; extra == 'dev'
Requires-Dist: isort; extra == 'dev'
Requires-Dist: notebook; extra == 'dev'
Requires-Dist: numpydoc; extra == 'dev'
Requires-Dist: pooch>=1.3; extra == 'dev'
Requires-Dist: pre-commit; extra == 'dev'
Requires-Dist: pydata-sphinx-theme; extra == 'dev'
Requires-Dist: pydocstyle; extra == 'dev'
Requires-Dist: pydocstyle[toml]; extra == 'dev'
Requires-Dist: pytest; extra == 'dev'
Requires-Dist: rstcheck; extra == 'dev'
Requires-Dist: ruff; extra == 'dev'
Requires-Dist: sphinx; extra == 'dev'
Requires-Dist: sphinx-copybutton; extra == 'dev'
Requires-Dist: sphinx-gallery>=0.18; extra == 'dev'
Requires-Dist: sphinxcontrib-bibtex; extra == 'dev'
Requires-Dist: toml-sort; extra == 'dev'
Requires-Dist: yamllint; extra == 'dev'
Provides-Extra: doc
Requires-Dist: ipykernel; extra == 'doc'
Requires-Dist: ipython; extra == 'doc'
Requires-Dist: ipywidgets; extra == 'doc'
Requires-Dist: notebook; extra == 'doc'
Requires-Dist: numpydoc; extra == 'doc'
Requires-Dist: pooch>=1.3; extra == 'doc'
Requires-Dist: pydata-sphinx-theme; extra == 'doc'
Requires-Dist: sphinx; extra == 'doc'
Requires-Dist: sphinx-copybutton; extra == 'doc'
Requires-Dist: sphinx-gallery>=0.18; extra == 'doc'
Requires-Dist: sphinxcontrib-bibtex; extra == 'doc'
Provides-Extra: lint
Requires-Dist: codespell; extra == 'lint'
Requires-Dist: isort; extra == 'lint'
Requires-Dist: pre-commit; extra == 'lint'
Requires-Dist: pydocstyle; extra == 'lint'
Requires-Dist: pydocstyle[toml]; extra == 'lint'
Requires-Dist: rstcheck; extra == 'lint'
Requires-Dist: ruff; extra == 'lint'
Requires-Dist: toml-sort; extra == 'lint'
Requires-Dist: yamllint; extra == 'lint'
Provides-Extra: test
Requires-Dist: coverage; extra == 'test'
Requires-Dist: pooch>=1.3; extra == 'test'
Requires-Dist: pytest; extra == 'test'
